autosentiment/__init__.py
autosentiment/code.py
autosentiment-1.2.6.dist-info/LICENSE.lic
autosentiment-1.2.6.dist-info/METADATA
autosentiment-1.2.6.dist-info/WHEEL
autosentiment-1.2.6.dist-info/top_level.txt
autosentiment-1.2.6.dist-info/RECORD
