Metadata-Version: 2.1
Name: autosentiment
Version: 1.2.6
Summary: An automatic sentiment analysis pakage
Home-page: https://github.com/CodeFighter03/autosentiment
Author: Sazin Reshed Samin
Author-email: sazinsamin50@gmail.com
License: UNKNOWN
Platform: UNKNOWN
Classifier: Programming Language :: Python :: 3
Classifier: License :: OSI Approved :: MIT License
Classifier: Operating System :: OS Independent
Requires-Python: >=3.6
